langchain_velatir/__init__.py
langchain_velatir/client.py
langchain_velatir/exceptions.py
langchain_velatir/middleware.py
langchain_velatir/types.py
langchain_velatir-0.0.3.dist-info/licenses/LICENSE
langchain_velatir-0.0.3.dist-info/METADATA
langchain_velatir-0.0.3.dist-info/WHEEL
langchain_velatir-0.0.3.dist-info/top_level.txt
langchain_velatir-0.0.3.dist-info/RECORD
