Metadata-Version: 2.4
Name: langchain-velatir
Version: 0.0.3
Summary: LangChain integration for Velatir - AI governance, compliance, and human-in-the-loop workflows
Author-email: Velatir <hello@velatir.com>
License: MIT
Project-URL: Homepage, https://www.velatir.com
Project-URL: Documentation, https://www.velatir.com/docs
Project-URL: Repository, https://github.com/velatir/langchain-velatir
Project-URL: Bug Tracker, https://github.com/velatir/langchain-velatir/issues
Project-URL: Changelog, https://github.com/velatir/langchain-velatir/blob/main/CHANGELOG.md
Project-URL: Source Code, https://github.com/velatir/langchain-velatir
Keywords: langchain,velatir,ai-governance,compliance,human-in-the-loop,guardrails,middleware,eu-ai-act,gdpr
Classifier: Development Status :: 3 - Alpha
Classifier: Intended Audience :: Developers
Classifier: License :: OSI Approved :: MIT License
Classifier: Programming Language :: Python :: 3
Classifier: Programming Language :: Python :: 3.10
Classifier: Programming Language :: Python :: 3.11
Classifier: Programming Language :: Python :: 3.12
Classifier: Programming Language :: Python :: 3.13
Classifier: Topic :: Software Development :: Libraries :: Python Modules
Classifier: Topic :: Scientific/Engineering :: Artificial Intelligence
Requires-Python: >=3.10
License-File: LICENSE
Requires-Dist: velatir>=1.0.0
Requires-Dist: langchain-core>=0.3.0
Requires-Dist: pydantic>=2.0.0
Provides-Extra: dev
Requires-Dist: pytest>=7.0.0; extra == "dev"
Requires-Dist: pytest-asyncio>=0.21.0; extra == "dev"
Requires-Dist: pytest-cov>=4.0.0; extra == "dev"
Requires-Dist: black>=23.0.0; extra == "dev"
Requires-Dist: ruff>=0.1.0; extra == "dev"
Requires-Dist: mypy>=1.0.0; extra == "dev"
Requires-Dist: build>=1.0.0; extra == "dev"
Requires-Dist: twine>=4.0.0; extra == "dev"
Dynamic: license-file
